README.md
setup.py
aeron_python_driver.egg-info/PKG-INFO
aeron_python_driver.egg-info/SOURCES.txt
aeron_python_driver.egg-info/dependency_links.txt
aeron_python_driver.egg-info/not-zip-safe
aeron_python_driver.egg-info/requires.txt
aeron_python_driver.egg-info/top_level.txt
aeronpy/driver/__init__.py
aeronpy/driver/aeron-all-1.15.1.jar
aeronpy/driver/archiving_media_driver.py
aeronpy/driver/media_driver.py