Metadata-Version: 1.1
Name: aeron-python-driver
Version: 1.15.1
Summary: Python wrapper for Aeron MediaDriver
Home-page: UNKNOWN
Author: Fairtide Pte.
Author-email: UNKNOWN
License: Apache 2.0
Platform: Posix; MacOS X; Windows
Classifier: Development Status :: 3 - Alpha
Classifier: Intended Audience :: Developers
Classifier: License :: OSI Approved :: Apache Software License
Classifier: Programming Language :: Python
Classifier: Programming Language :: Python :: 3 :: Only
Classifier: Operating System :: OS Independent
Classifier: Topic :: Communications
Classifier: Topic :: Internet
Classifier: Topic :: Software Development
Classifier: Topic :: System
Classifier: Topic :: System :: Networking
